Metadata-Version: 2.1
Name: oneimage
Version: 1.2.0
Summary: A simple python lib to create poster image with define data.
Home-page: https://github.com/sintrb/oneimage/
Author: trb
Author-email: sintrb@gmail.com
License: UNKNOWN
Keywords: oneimage,image,picture
Platform: UNKNOWN
